{
  "bca": 0.3685714285714286,
  "std_bca": 0.008164965809277286,
  "kappa": 0.1600196986470173,
  "ci_lo": 0.2863095238095238,
  "ci_hi": 0.3864087301587301,
  "fit_time": 2.0440518856048584,
  "fit_time_warm": 2.1384337544441223,
  "train_fit_time": 2.0220470905303953,
  "train_fit_time_warm": 2.1162165999412537,
  "k_minutes": 15.0,
  "n_cal_trials": 224,
  "protocol": "k_minute_sweep",
  "subject_id": 2,
  "repeats": [
    {
      "bca": 0.37857142857142856,
      "kappa": 0.1737237831420657,
      "ci_lo": 0.3113095238095238,
      "ci_hi": 0.3864087301587301,
      "p_value": 0.03,
      "significant": true,
      "n_trials": 58,
      "fit_time": 1.6665244102478027,
      "train_fit_time": 1.645369052886963,
      "k_minutes": 15.0,
      "n_cal_trials": 224,
      "repeat": 0,
      "protocol": "k_minute_sweep",
      "subject_id": 2
    },
    {
      "bca": 0.37857142857142856,
      "kappa": 0.1737237831420657,
      "ci_lo": 0.3113095238095238,
      "ci_hi": 0.3864087301587301,
      "p_value": 0.03,
      "significant": true,
      "n_trials": 58,
      "fit_time": 1.5937738418579102,
      "train_fit_time": 1.5739398002624512,
      "k_minutes": 15.0,
      "n_cal_trials": 224,
      "repeat": 1,
      "protocol": "k_minute_sweep",
      "subject_id": 2
    },
    {
      "bca": 0.36190476190476184,
      "kappa": 0.1507716660071231,
      "ci_lo": 0.26964285714285713,
      "ci_hi": 0.3864087301587301,
      "p_value": 0.035,
      "significant": true,
      "n_trials": 58,
      "fit_time": 1.9006848335266113,
      "train_fit_time": 1.8767292499542236,
      "k_minutes": 15.0,
      "n_cal_trials": 224,
      "repeat": 2,
      "protocol": "k_minute_sweep",
      "subject_id": 2
    },
    {
      "bca": 0.36190476190476184,
      "kappa": 0.15110759493670878,
      "ci_lo": 0.26964285714285713,
      "ci_hi": 0.3864087301587301,
      "p_value": 0.035,
      "significant": true,
      "n_trials": 58,
      "fit_time": 3.155768632888794,
      "train_fit_time": 3.132978677749634,
      "k_minutes": 15.0,
      "n_cal_trials": 224,
      "repeat": 3,
      "protocol": "k_minute_sweep",
      "subject_id": 2
    },
    {
      "bca": 0.36190476190476184,
      "kappa": 0.1507716660071231,
      "ci_lo": 0.26964285714285713,
      "ci_hi": 0.3864087301587301,
      "p_value": 0.035,
      "significant": true,
      "n_trials": 58,
      "fit_time": 1.9035077095031738,
      "train_fit_time": 1.881218671798706,
      "k_minutes": 15.0,
      "n_cal_trials": 224,
      "repeat": 4,
      "protocol": "k_minute_sweep",
      "subject_id": 2
    }
  ],
  "_meta": {
    "dataset": "bciciv2a",
    "backbone": "labram",
    "method": "foundation_sft_finetune",
    "saved_at": "2026-06-04T01:20:25.260583"
  }
}