{
  "bca": 0.7410256410256411,
  "std_bca": 0.014553238480087124,
  "kappa": 0.639226820449124,
  "ci_lo": 0.6561904761904762,
  "ci_hi": 0.853501400560224,
  "fit_time": 0.3026937961578369,
  "fit_time_warm": 0.3018222451210022,
  "train_fit_time": 0.2989262099727057,
  "train_fit_time_warm": 0.298152112722164,
  "k_minutes": 10.0,
  "n_cal_trials": 148,
  "protocol": "k_minute_sweep",
  "subject_id": 1,
  "repeats": [
    {
      "bca": 0.7504578754578755,
      "kappa": 0.652694610778443,
      "ci_lo": 0.6904761904761905,
      "ci_hi": 0.8347338935574229,
      "p_value": 0.0,
      "significant": true,
      "n_trials": 58,
      "fit_time": 0.3061800003051758,
      "train_fit_time": 0.3020225989748724,
      "k_minutes": 10.0,
      "n_cal_trials": 148,
      "repeat": 0,
      "protocol": "k_minute_sweep",
      "subject_id": 1
    },
    {
      "bca": 0.762973137973138,
      "kappa": 0.6758483033932136,
      "ci_lo": 0.6654761904761906,
      "ci_hi": 0.8879551820728291,
      "p_value": 0.0,
      "significant": true,
      "n_trials": 58,
      "fit_time": 0.30071425437927246,
      "train_fit_time": 0.2973036749754101,
      "k_minutes": 10.0,
      "n_cal_trials": 148,
      "repeat": 1,
      "protocol": "k_minute_sweep",
      "subject_id": 1
    },
    {
      "bca": 0.7312271062271062,
      "kappa": 0.6288,
      "ci_lo": 0.6654761904761906,
      "ci_hi": 0.8347338935574229,
      "p_value": 0.0,
      "significant": true,
      "n_trials": 58,
      "fit_time": 0.30379724502563477,
      "train_fit_time": 0.2999216739553958,
      "k_minutes": 10.0,
      "n_cal_trials": 148,
      "repeat": 2,
      "protocol": "k_minute_sweep",
      "subject_id": 1
    },
    {
      "bca": 0.7213064713064714,
      "kappa": 0.6074840764331211,
      "ci_lo": 0.6297619047619047,
      "ci_hi": 0.8403361344537815,
      "p_value": 0.0,
      "significant": true,
      "n_trials": 58,
      "fit_time": 0.3053758144378662,
      "train_fit_time": 0.30174177198205143,
      "k_minutes": 10.0,
      "n_cal_trials": 148,
      "repeat": 3,
      "protocol": "k_minute_sweep",
      "subject_id": 1
    },
    {
      "bca": 0.7391636141636142,
      "kappa": 0.6313071116408423,
      "ci_lo": 0.6297619047619047,
      "ci_hi": 0.8697478991596639,
      "p_value": 0.0,
      "significant": true,
      "n_trials": 58,
      "fit_time": 0.29740166664123535,
      "train_fit_time": 0.2936413299757987,
      "k_minutes": 10.0,
      "n_cal_trials": 148,
      "repeat": 4,
      "protocol": "k_minute_sweep",
      "subject_id": 1
    }
  ],
  "_meta": {
    "dataset": "bciciv2a",
    "backbone": "mirepnet",
    "method": "foundation_sft_kadaptive_anchored_cld",
    "saved_at": "2026-06-04T03:10:43.175563"
  }
}