{
  "bca": 0.4314285714285714,
  "std_bca": 0.006925256939166182,
  "kappa": 0.24496053742524868,
  "ci_lo": 0.38402777777777775,
  "ci_hi": 0.4345238095238095,
  "fit_time": 0.3011934280395508,
  "fit_time_warm": 0.3009442090988159,
  "train_fit_time": 0.2959385817754082,
  "train_fit_time_warm": 0.2959670964773977,
  "k_minutes": 1.0,
  "n_cal_trials": 12,
  "protocol": "k_minute_sweep",
  "subject_id": 2,
  "repeats": [
    {
      "bca": 0.42738095238095236,
      "kappa": 0.24017467248908297,
      "ci_lo": 0.3888888888888889,
      "ci_hi": 0.42738095238095236,
      "p_value": 0.005,
      "significant": true,
      "n_trials": 58,
      "fit_time": 0.30219030380249023,
      "train_fit_time": 0.2958245229674503,
      "k_minutes": 1.0,
      "n_cal_trials": 12,
      "repeat": 0,
      "protocol": "k_minute_sweep",
      "subject_id": 2
    },
    {
      "bca": 0.4452380952380952,
      "kappa": 0.2631996824136562,
      "ci_lo": 0.3888888888888889,
      "ci_hi": 0.4452380952380952,
      "p_value": 0.005,
      "significant": true,
      "n_trials": 58,
      "fit_time": 0.3001582622528076,
      "train_fit_time": 0.2950108770164661,
      "k_minutes": 1.0,
      "n_cal_trials": 12,
      "repeat": 1,
      "protocol": "k_minute_sweep",
      "subject_id": 2
    },
    {
      "bca": 0.42857142857142855,
      "kappa": 0.24077746925823085,
      "ci_lo": 0.3923611111111111,
      "ci_hi": 0.42857142857142855,
      "p_value": 0.005,
      "significant": true,
      "n_trials": 58,
      "fit_time": 0.3090200424194336,
      "train_fit_time": 0.30419980495935306,
      "k_minutes": 1.0,
      "n_cal_trials": 12,
      "repeat": 2,
      "protocol": "k_minute_sweep",
      "subject_id": 2
    },
    {
      "bca": 0.42857142857142855,
      "kappa": 0.2404761904761905,
      "ci_lo": 0.3611111111111111,
      "ci_hi": 0.444047619047619,
      "p_value": 0.005,
      "significant": true,
      "n_trials": 58,
      "fit_time": 0.3009183406829834,
      "train_fit_time": 0.2958010779111646,
      "k_minutes": 1.0,
      "n_cal_trials": 12,
      "repeat": 3,
      "protocol": "k_minute_sweep",
      "subject_id": 2
    },
    {
      "bca": 0.42738095238095236,
      "kappa": 0.24017467248908297,
      "ci_lo": 0.3888888888888889,
      "ci_hi": 0.42738095238095236,
      "p_value": 0.005,
      "significant": true,
      "n_trials": 58,
      "fit_time": 0.29368019104003906,
      "train_fit_time": 0.2888566260226071,
      "k_minutes": 1.0,
      "n_cal_trials": 12,
      "repeat": 4,
      "protocol": "k_minute_sweep",
      "subject_id": 2
    }
  ],
  "_meta": {
    "dataset": "bciciv2a",
    "backbone": "eegnet",
    "method": "kadaptive_anchored_cld",
    "saved_at": "2026-06-04T03:05:30.225951"
  }
}