{
  "bca": 0.9321428571428572,
  "std_bca": 0.0,
  "kappa": 0.9080095162569389,
  "ci_lo": 0.9041666666666666,
  "ci_hi": 0.9375,
  "fit_time": 0.9185299396514892,
  "fit_time_warm": 0.29847997426986694,
  "train_fit_time": 0.29318273056996985,
  "train_fit_time_warm": 0.29484022546967026,
  "k_minutes": 0.5,
  "n_cal_trials": 4,
  "protocol": "k_minute_sweep",
  "subject_id": 3,
  "repeats": [
    {
      "bca": 0.9321428571428572,
      "kappa": 0.9080095162569389,
      "ci_lo": 0.9041666666666667,
      "ci_hi": 0.9375,
      "p_value": 0.0,
      "significant": true,
      "n_trials": 58,
      "fit_time": 3.3987298011779785,
      "train_fit_time": 0.2865527509711683,
      "k_minutes": 0.5,
      "n_cal_trials": 4,
      "repeat": 0,
      "protocol": "k_minute_sweep",
      "subject_id": 3
    },
    {
      "bca": 0.9321428571428572,
      "kappa": 0.9080095162569389,
      "ci_lo": 0.9041666666666667,
      "ci_hi": 0.9375,
      "p_value": 0.0,
      "significant": true,
      "n_trials": 58,
      "fit_time": 0.29185009002685547,
      "train_fit_time": 0.28817772696493194,
      "k_minutes": 0.5,
      "n_cal_trials": 4,
      "repeat": 1,
      "protocol": "k_minute_sweep",
      "subject_id": 3
    },
    {
      "bca": 0.9321428571428572,
      "kappa": 0.9080095162569389,
      "ci_lo": 0.9041666666666667,
      "ci_hi": 0.9375,
      "p_value": 0.0,
      "significant": true,
      "n_trials": 58,
      "fit_time": 0.2853407859802246,
      "train_fit_time": 0.28186096902936697,
      "k_minutes": 0.5,
      "n_cal_trials": 4,
      "repeat": 2,
      "protocol": "k_minute_sweep",
      "subject_id": 3
    },
    {
      "bca": 0.9321428571428572,
      "kappa": 0.9080095162569389,
      "ci_lo": 0.9041666666666667,
      "ci_hi": 0.9375,
      "p_value": 0.0,
      "significant": true,
      "n_trials": 58,
      "fit_time": 0.3002891540527344,
      "train_fit_time": 0.2968137799180113,
      "k_minutes": 0.5,
      "n_cal_trials": 4,
      "repeat": 3,
      "protocol": "k_minute_sweep",
      "subject_id": 3
    },
    {
      "bca": 0.9321428571428572,
      "kappa": 0.9080095162569389,
      "ci_lo": 0.9041666666666667,
      "ci_hi": 0.9375,
      "p_value": 0.0,
      "significant": true,
      "n_trials": 58,
      "fit_time": 0.3164398670196533,
      "train_fit_time": 0.31250842596637085,
      "k_minutes": 0.5,
      "n_cal_trials": 4,
      "repeat": 4,
      "protocol": "k_minute_sweep",
      "subject_id": 3
    }
  ],
  "_meta": {
    "dataset": "bciciv2a",
    "backbone": "labram",
    "method": "foundation_sft_kadaptive_anchored_cld",
    "saved_at": "2026-06-04T03:09:33.862792"
  }
}